fs2dicom/__init__.py
fs2dicom/_version.py
fs2dicom/fs2dicom.py
fs2dicom/seg.py
fs2dicom/sr.py
fs2dicom/utils.py
fs2dicom/templates/fs-aseg-sr-template.json
fs2dicom/templates/fs-aseg.json
fs2dicom/tests/__init__.py
fs2dicom/tests/conftest.py
fs2dicom/tests/test_examples.py
fs2dicom-0.1.2.dist-info/METADATA
fs2dicom-0.1.2.dist-info/RECORD
fs2dicom-0.1.2.dist-info/WHEEL
fs2dicom-0.1.2.dist-info/entry_points.txt
fs2dicom-0.1.2.dist-info/top_level.txt
