Metadata-Version: 2.1
Name: fs2dicom
Version: 0.1.2
Summary: Create DICOM Segmentation Image and Structured Report objects from FreeSurfer segmentations
Home-page: https://github.com/corticometrics/fs2dicom
Author: CorticoMetrics
Author-email: ltirrell@corticometrics.com
License: BSD (3-clause)
Platform: UNKNOWN
Classifier: Development Status :: 2 - Pre-Alpha
Classifier: Natural Language :: English
Classifier: Programming Language :: Python :: 3
Requires-Dist: click
Requires-Dist: docker
Requires-Dist: jinja2
Requires-Dist: numpy
Requires-Dist: pandas
Requires-Dist: pydicom
